mouse_jerk/clicker.py
mouse_jerk/script.py
mouse_jerk-0.4.2.dist-info/entry_points.txt
mouse_jerk-0.4.2.dist-info/WHEEL
mouse_jerk-0.4.2.dist-info/METADATA
mouse_jerk-0.4.2.dist-info/RECORD
