Metadata-Version: 2.1
Name: mouse-jerk
Version: 0.4.2
Summary: Small app, that help your PC to not fall asleep.
Home-page: https://github.com/gstr169/mouse_jerk
Author: d.finko
Author-email: dmit.finn@yandex.ru
Requires-Python: >=3.8.5,<4.0.0
Classifier: Programming Language :: Python :: 3
Requires-Dist: pynput (>=1.7.1,<2.0.0)
Project-URL: Repository, https://github.com/gstr169/mouse_jerk
